glass/ext/gowerst/__init__.py
glass/ext/gowerst/_cosmology.py
glass/ext/gowerst/_gowerst.py
glass/ext/gowerst/_parfile.py
glass.ext.gowerst-0.1.dist-info/METADATA
glass.ext.gowerst-0.1.dist-info/WHEEL
glass.ext.gowerst-0.1.dist-info/licenses/LICENSE.txt
glass.ext.gowerst-0.1.dist-info/RECORD
