Metadata-Version: 2.4
Name: glass.ext.gowerst
Version: 0.1
Summary: GLASS extension for loading GowerSt simulations
Project-URL: Homepage, https://github.com/glass-dev/glass.ext.gowerst
Project-URL: Documentation, https://glass.readthedocs.io/projects/gowerst/
Project-URL: Issues, https://github.com/glass-dev/glass.ext.gowerst/issues
Author-email: Nicolas Tessore <n.tessore@ucl.ac.uk>
License: MIT License
License-File: LICENSE.txt
Classifier: License :: OSI Approved :: MIT License
Classifier: Operating System :: OS Independent
Classifier: Programming Language :: Python :: 3
Requires-Python: >=3.10
Requires-Dist: glass>=2025.1
Requires-Dist: h5py
Requires-Dist: healpy
Requires-Dist: numpy
Requires-Dist: scipy
Provides-Extra: docs
Requires-Dist: furo; extra == 'docs'
Requires-Dist: numpydoc; extra == 'docs'
Requires-Dist: sphinx; extra == 'docs'
Requires-Dist: sphinxcontrib-katex; extra == 'docs'
Provides-Extra: test
Requires-Dist: pytest; extra == 'test'
